intc_lsp/__init__.py
intc_lsp/cli.py
intc_lsp/server.py
intc_lsp/version.py
intc_lsp/version.txt
intc_lsp/csrc/json/Cargo.toml
intc_lsp/csrc/json/README.md
intc_lsp/csrc/json/binding.gyp
intc_lsp/csrc/json/grammar.js
intc_lsp/csrc/json/grammar_base.js
intc_lsp/csrc/json/package.json
intc_lsp/csrc/json/bindings/node/binding.cc
intc_lsp/csrc/json/bindings/node/index.js
intc_lsp/csrc/json/bindings/rust/build.rs
intc_lsp/csrc/json/bindings/rust/lib.rs
intc_lsp/csrc/json/src/grammar.json
intc_lsp/csrc/json/src/node-types.json
intc_lsp/csrc/json/src/parser.c
intc_lsp/csrc/json/src/tree_sitter/parser.h
intc_lsp/csrc/yaml/Cargo.toml
intc_lsp/csrc/yaml/README.md
intc_lsp/csrc/yaml/binding.gyp
intc_lsp/csrc/yaml/grammar.js
intc_lsp/csrc/yaml/package.json
intc_lsp/csrc/yaml/bindings/node/binding.cc
intc_lsp/csrc/yaml/bindings/node/index.js
intc_lsp/csrc/yaml/bindings/rust/build.rs
intc_lsp/csrc/yaml/bindings/rust/lib.rs
intc_lsp/csrc/yaml/src/grammar.json
intc_lsp/csrc/yaml/src/node-types.json
intc_lsp/csrc/yaml/src/parser.c
intc_lsp/csrc/yaml/src/scanner.cc
intc_lsp/csrc/yaml/src/schema.generated.cc
intc_lsp/csrc/yaml/src/tree_sitter/parser.h
intc_lsp/lib/__init__.py
intc_lsp/lib/json_linux_ts.so
intc_lsp/lib/json_mac_ts.so
intc_lsp/lib/json_ts.so
intc_lsp/lib/yaml_linux_ts.so
intc_lsp/lib/yaml_mac_ts.so
intc_lsp/lib/yaml_ts.so
intc_lsp/lib/yaml_{sys_post_fix}_ts.so
intc_lsp/src/__init__.py
intc_lsp/src/edit.py
intc_lsp/src/parser_json.py
intc_lsp/src/parser_yaml.py
intc_lsp/src/resolve.py
intc_lsp/src/trace.py
intc_lsp-0.1.1.dist-info/LICENSE
intc_lsp-0.1.1.dist-info/METADATA
intc_lsp-0.1.1.dist-info/WHEEL
intc_lsp-0.1.1.dist-info/entry_points.txt
intc_lsp-0.1.1.dist-info/top_level.txt
intc_lsp-0.1.1.dist-info/RECORD
