Metadata-Version: 2.1
Name: intc-lsp
Version: 0.1.1
Summary: intc-lsp: intc language server
Home-page: https://github.com/cstsunfu/intc
Author-email: cstsunfu <cstsunfu@gmail.com>
License: Apache License 2.0
Keywords: intc,lsp,intc-lsp
Classifier: Programming Language :: Python :: 3.8
Classifier: Programming Language :: Python :: 3.9
Classifier: License :: OSI Approved :: Apache Software License
Requires-Python: >=3.8
License-File: LICENSE
Requires-Dist: intc <0.2,>=0.1
Requires-Dist: platformdirs >=4.2.0
Requires-Dist: pygls >=1.1
Requires-Dist: tree-sitter <=0.22,>=0.21.1
